tests/__init__.py
tests/test_typedispatch.py
typedispatch/__init__.py
typedispatch/typedispatch.py
typedispatch-1.1.0.dist-info/LICENSE
typedispatch-1.1.0.dist-info/METADATA
typedispatch-1.1.0.dist-info/WHEEL
typedispatch-1.1.0.dist-info/top_level.txt
typedispatch-1.1.0.dist-info/RECORD
