Metadata-Version: 2.1
Name: typedispatch
Version: 1.1.0
Summary: TypeDispatch is a Python utility for registering and dispatching functions based on object types and predicates, supporting inheritance through method resolution order (MRO).
Home-page: https://github.com/ruitcatarino/typedispatch
Author: Rui Catarino
Classifier: Development Status :: 5 - Production/Stable
Classifier: Programming Language :: Python :: 3
Classifier: Intended Audience :: Developers
Classifier: License :: OSI Approved :: MIT License
Classifier: Operating System :: OS Independent
License-File: LICENSE
